MANIFEST.in
README.md
setup.py
signpdf.py
signpdf.egg-info/PKG-INFO
signpdf.egg-info/SOURCES.txt
signpdf.egg-info/dependency_links.txt
signpdf.egg-info/entry_points.txt
signpdf.egg-info/requires.txt
signpdf.egg-info/top_level.txt