Metadata-Version: 1.0
Name: signpdf
Version: 0.0.2
Summary: Utility for adding signatures images to PDF documents
Home-page: https://github.com/yourcelf/signpdf
Author: Charlie DeTar
Author-email: cfd@media.mit.edu
License: MIT
Platform: UNKNOWN
